performance_monitor.py
performance_monitor-0.0.1.dist-info/LICENSE.txt
performance_monitor-0.0.1.dist-info/METADATA
performance_monitor-0.0.1.dist-info/WHEEL
performance_monitor-0.0.1.dist-info/top_level.txt
performance_monitor-0.0.1.dist-info/RECORD
