Metadata-Version: 2.1
Name: performance-monitor
Version: 0.0.1
Summary: Simple Decorator to check the time took by a function to get executed.
Home-page: https://github.com/niksingh710/performance-monitor
Author: Nikhil Singh
Author-email: nik.singh710@gmail.com
License: UNKNOWN
Platform: UNKNOWN
Classifier: License :: OSI Approved :: GNU General Public License v3 (GPLv3)
Classifier: Operating System :: OS Independent
